bugyi/tools/__init__.py
bugyi/tools/anagrams.py
bugyi/tools/py.typed
bugyi/tools/shlib.py
bugyi/tools/data/__init__.py
bugyi/tools/data/shlib/__init__.py
bugyi/tools/data/shlib/bugyi.sh
bugyi.tools-0.2.2.dist-info/METADATA
bugyi.tools-0.2.2.dist-info/WHEEL
bugyi.tools-0.2.2.dist-info/entry_points.txt
bugyi.tools-0.2.2.dist-info/top_level.txt
bugyi.tools-0.2.2.dist-info/RECORD
